railtownai/__init__.py
railtownai/api_client.py
railtownai/breadcrumbs.py
railtownai/config.py
railtownai/core.py
railtownai/handler.py
railtownai/models.py
railtownai-2.0.7.dist-info/licenses/LICENSE
railtownai-2.0.7.dist-info/WHEEL
railtownai-2.0.7.dist-info/METADATA
railtownai-2.0.7.dist-info/RECORD
