Metadata-Version: 2.4
Name: railtownai
Version: 2.0.7
Summary: Railtown AI Python SDK for tracking errors and exceptions in your Python applications
Author-email: Guan Zheng Huang <guan@railtown.ai>, Jaime Bueza <jaime@railtown.ai>, Logan Underwood <logan@railtown.ai>
Classifier: License :: OSI Approved :: MIT License
License-File: LICENSE
Requires-Dist: requests >=2.31,<3
Requires-Dist: pydantic >= 2.5.3,<3
Requires-Dist: requests-mock >= 1.12.1
Requires-Dist: python-dotenv == 1.0.0
Requires-Dist: ruff >= 0.13.0
Requires-Dist: pytest >=7.1.2 ; extra == "test"
Requires-Dist: tomli ; extra == "test" and ( python_version < '3.11')
Project-URL: Home, https://railtown.ai
Provides-Extra: test
